mymongo/__init__.py
mymongo/__main__.py
mymongo/app.py
mymongo/constants.py
mymongo/decorators.py
mymongo/database/__init__.py
mymongo/database/mongodb.py
mymongo/utils/__init__.py
mymongo/utils/print_utils.py
mongo_user_manager-0.0.2.dist-info/LICENSE
mongo_user_manager-0.0.2.dist-info/METADATA
mongo_user_manager-0.0.2.dist-info/WHEEL
mongo_user_manager-0.0.2.dist-info/entry_points.txt
mongo_user_manager-0.0.2.dist-info/top_level.txt
mongo_user_manager-0.0.2.dist-info/RECORD
